ewi_usb_config/__init__.py
ewi_usb_config/__main__.py
ewi_usb_config/cli.py
ewi_usb_config/ewidata.py
ewi_usb_config/version.py
ewi_usb_config_cli-0.1.0.dist-info/METADATA
ewi_usb_config_cli-0.1.0.dist-info/WHEEL
ewi_usb_config_cli-0.1.0.dist-info/entry_points.txt
ewi_usb_config_cli-0.1.0.dist-info/licenses/LICENSE
ewi_usb_config_cli-0.1.0.dist-info/RECORD
