Metadata-Version: 2.3
Name: ewi-usb-config-cli
Version: 0.1.0
Summary: Configure an Akai EWI USB MIDI wind controller via MIDI from the command line
Project-URL: Homepage, https://github.com/SpotlightKid/ewi-usb-config-cli
Project-URL: Source, https://github.com/SpotlightKid/ewi-usb-config-cli
Project-URL: Issues, https://github.com/SpotlightKid/ewi-usb-config-cli/issues
Author-email: Christopher Arndt <chris@chrisarndt.de>
License-Expression: MIT
License-File: LICENSE
Keywords: akai,ewi,ewi usb,midi,sysex,wind controller
Classifier: Development Status :: 4 - Beta
Classifier: Environment :: Console
Classifier: Intended Audience :: End Users/Desktop
Classifier: License :: OSI Approved :: MIT License
Classifier: Programming Language :: Python
Classifier: Programming Language :: Python :: 3.10
Classifier: Programming Language :: Python :: 3.11
Classifier: Programming Language :: Python :: 3.12
Classifier: Programming Language :: Python :: Implementation :: CPython
Classifier: Topic :: Multimedia :: Sound/Audio :: MIDI
Requires-Python: >=3.10
Requires-Dist: python-rtmidi~=1.5.8
